{
  "id": "QSO",
  "viewports": [
    { "label": "phone", "width": 320, "height": 480 },
    { "label": "tablet", "width": 1024, "height": 768 }
  ],
  "onBeforeScript": "puppet/onBefore.js",
  "onReadyScript": "puppet/onReady.js",
  "scenarios": [
    {
      "label": "BUTTON DEFAULT",
      "cookiePath": "backstop_data/engine_scripts/cookies.json",
      "url": "http://localhost:6006/iframe.html?viewMode=story&id=button--default",
      "referenceUrl": "",
      "readyEvent": "",
      "readySelector": "#component-container",
      "delay": 0,
      "hideSelectors": [],
      "removeSelectors": [],
      "hoverSelector": "",
      "clickSelector": "",
      "postInteractionWait": 2000,
      "selectors": ["#component-container"],
      "selectorExpansion": true,
      "expect": 0,
      "misMatchThreshold": 0.1,
      "requireSameDimensions": true
    },
    {
      "label": "BUTTON REGULAR",
      "cookiePath": "backstop_data/engine_scripts/cookies.json",
      "url": "http://localhost:6006/iframe.html?viewMode=story&id=button--regular",
      "referenceUrl": "",
      "readyEvent": "",
      "readySelector": "#component-container",
      "delay": 0,
      "hideSelectors": [],
      "removeSelectors": [],
      "hoverSelector": "",
      "clickSelector": "",
      "postInteractionWait": 2000,
      "selectors": ["#component-container"],
      "selectorExpansion": true,
      "expect": 0,
      "misMatchThreshold": 0.1,
      "requireSameDimensions": true
    },
    {
      "label": "BUTTON STYLED SYSTEM PROPS",
      "cookiePath": "backstop_data/engine_scripts/cookies.json",
      "url": "http://localhost:6006/iframe.html?viewMode=story&id=button--styled-system-props",
      "referenceUrl": "",
      "readyEvent": "",
      "readySelector": "#component-container",
      "delay": 0,
      "hideSelectors": [],
      "removeSelectors": [],
      "hoverSelector": "",
      "clickSelector": "",
      "postInteractionWait": 2000,
      "selectors": ["#component-container"],
      "selectorExpansion": true,
      "expect": 0,
      "misMatchThreshold": 0.1,
      "requireSameDimensions": true
    },
    {
      "label": "BUTTON RENAMED: BUTTON WITH HOOKS",
      "cookiePath": "backstop_data/engine_scripts/cookies.json",
      "url": "http://localhost:6006/iframe.html?viewMode=story&id=button--button-with-hooks",
      "referenceUrl": "",
      "readyEvent": "",
      "readySelector": "#component-container",
      "delay": 0,
      "hideSelectors": [],
      "removeSelectors": [],
      "hoverSelector": "",
      "clickSelector": "",
      "postInteractionWait": 2000,
      "selectors": ["#component-container"],
      "selectorExpansion": true,
      "expect": 0,
      "misMatchThreshold": 0.1,
      "requireSameDimensions": true
    },
    {
      "label": "INPUT DEFAULT",
      "cookiePath": "backstop_data/engine_scripts/cookies.json",
      "url": "http://localhost:6006/iframe.html?viewMode=story&id=input--default",
      "referenceUrl": "",
      "readyEvent": "",
      "readySelector": "#component-container",
      "delay": 0,
      "hideSelectors": [],
      "removeSelectors": [],
      "hoverSelector": "",
      "clickSelector": "",
      "postInteractionWait": 2000,
      "selectors": ["#component-container"],
      "selectorExpansion": true,
      "expect": 0,
      "misMatchThreshold": 0.1,
      "requireSameDimensions": true
    },
    {
      "label": "INPUT REGULAR",
      "cookiePath": "backstop_data/engine_scripts/cookies.json",
      "url": "http://localhost:6006/iframe.html?viewMode=story&id=input--regular",
      "referenceUrl": "",
      "readyEvent": "",
      "readySelector": "#component-container",
      "delay": 0,
      "hideSelectors": [],
      "removeSelectors": [],
      "hoverSelector": "",
      "clickSelector": "",
      "postInteractionWait": 2000,
      "selectors": ["#component-container"],
      "selectorExpansion": true,
      "expect": 0,
      "misMatchThreshold": 0.1,
      "requireSameDimensions": true
    },
    {
      "label": "INPUT DISABLED",
      "cookiePath": "backstop_data/engine_scripts/cookies.json",
      "url": "http://localhost:6006/iframe.html?viewMode=story&id=input--disabled",
      "referenceUrl": "",
      "readyEvent": "",
      "readySelector": "#component-container",
      "delay": 0,
      "hideSelectors": [],
      "removeSelectors": [],
      "hoverSelector": "",
      "clickSelector": "",
      "postInteractionWait": 2000,
      "selectors": ["#component-container"],
      "selectorExpansion": true,
      "expect": 0,
      "misMatchThreshold": 0.1,
      "requireSameDimensions": true
    },
    {
      "label": "NAVBAR DEFAULT",
      "cookiePath": "backstop_data/engine_scripts/cookies.json",
      "url": "http://localhost:6006/iframe.html?viewMode=story&id=navbar--default",
      "referenceUrl": "",
      "readyEvent": "",
      "readySelector": "#component-container",
      "delay": 0,
      "hideSelectors": [],
      "removeSelectors": [],
      "hoverSelector": "",
      "clickSelector": "",
      "postInteractionWait": 2000,
      "selectors": ["#component-container"],
      "selectorExpansion": true,
      "expect": 0,
      "misMatchThreshold": 0.1,
      "requireSameDimensions": true
    },
    {
      "label": "TEXT DEFAULT",
      "cookiePath": "backstop_data/engine_scripts/cookies.json",
      "url": "http://localhost:6006/iframe.html?viewMode=story&id=text--default",
      "referenceUrl": "",
      "readyEvent": "",
      "readySelector": "#component-container",
      "delay": 0,
      "hideSelectors": [],
      "removeSelectors": [],
      "hoverSelector": "",
      "clickSelector": "",
      "postInteractionWait": 2000,
      "selectors": ["#component-container"],
      "selectorExpansion": true,
      "expect": 0,
      "misMatchThreshold": 0.1,
      "requireSameDimensions": true
    },
    {
      "label": "TEXT AS ANOTHER ELEMENT",
      "cookiePath": "backstop_data/engine_scripts/cookies.json",
      "url": "http://localhost:6006/iframe.html?viewMode=story&id=text--as-another-element",
      "referenceUrl": "",
      "readyEvent": "",
      "readySelector": "#component-container",
      "delay": 0,
      "hideSelectors": [],
      "removeSelectors": [],
      "hoverSelector": "",
      "clickSelector": "",
      "postInteractionWait": 2000,
      "selectors": ["#component-container"],
      "selectorExpansion": true,
      "expect": 0,
      "misMatchThreshold": 0.1,
      "requireSameDimensions": true
    }
  ],
  "paths": {
    "bitmaps_reference": "backstop_data/bitmaps_reference",
    "bitmaps_test": "backstop_data/bitmaps_test",
    "engine_scripts": "backstop_data/engine_scripts",
    "html_report": "backstop_data/html_report",
    "ci_report": "backstop_data/ci_report"
  },
  "report": ["browser"],
  "engine": "playwright",
  "engineOptions": { "args": ["--no-sandbox"] },
  "asyncCaptureLimit": 5,
  "asyncCompareLimit": 50,
  "debug": false,
  "debugWindow": false
}
